{
  "video_info": {
    "scene_index": 0,
    "video_filename": "video_00000.mp4",
    "scenario": "double",
    "setting": "basic",
    "total_frames": 125
  },
  "qa_pairs": [
    {
      "question": "Does the cyan metal sphere's collision with the purple metal cylinder affect the purple metal cylinder's motion?",
      "answer": "Yes",
      "question_type": "causality_identification",
      "question_rung": "discovery",
      "answer_type": "yes_no"
    },
    {
      "question": "Does the purple metal cube's collision with the cyan metal sphere affect the purple metal cylinder's motion?",
      "answer": "Yes",
      "question_type": "causality_identification",
      "question_rung": "discovery",
      "answer_type": "yes_no"
    },
    {
      "question": "Does the yellow metal cylinder's collision with the purple metal cube affect the purple metal cylinder's motion?",
      "answer": "Yes",
      "question_type": "causality_identification",
      "question_rung": "discovery",
      "answer_type": "yes_no"
    },
    {
      "question": "Why did the purple metal cylinder move?",
      "answer": [
        3
      ],
      "question_type": "causal_attribution",
      "question_rung": "discovery",
      "answer_type": "multi_choice",
      "options": [
        "Because the yellow metal cylinder collided with the purple metal cube.",
        "Because the purple metal cylinder moved spontaneously.",
        "Because the purple metal cube did not collide with the cyan metal sphere.",
        "Because the cyan metal sphere collided with the purple metal cylinder."
      ]
    },
    {
      "question": "If we force the purple metal cube to collide with the cyan metal sphere, will the cyan metal sphere cause the purple metal cylinder to move?",
      "answer": "No",
      "question_type": "individual_causal_effect",
      "question_rung": "intervention",
      "answer_type": "yes_no"
    },
    {
      "question": "If we force the yellow metal cylinder not to collide with the purple metal cube, will the cyan metal sphere cause the purple metal cylinder to move?",
      "answer": "No",
      "question_type": "individual_causal_effect",
      "question_rung": "intervention",
      "answer_type": "yes_no"
    },
    {
      "question": "If we force the yellow metal cylinder not to collide with the purple metal cube, will the purple metal cube cause the purple metal cylinder to stay stationary?",
      "answer": "Yes",
      "question_type": "individual_causal_effect",
      "question_rung": "intervention",
      "answer_type": "yes_no"
    },
    {
      "question": "If the cyan metal sphere had not collided with the purple metal cylinder, would the purple metal cylinder still have moved?",
      "answer": "No",
      "question_type": "counterfactual_reasoning",
      "question_rung": "counterfactual",
      "answer_type": "yes_no"
    },
    {
      "question": "If the purple metal cube had collided with the cyan metal sphere, would the purple metal cylinder still have moved?",
      "answer": "No",
      "question_type": "counterfactual_reasoning",
      "question_rung": "counterfactual",
      "answer_type": "yes_no"
    },
    {
      "question": "If the yellow metal cylinder had not collided with the purple metal cube, would the purple metal cylinder still have moved?",
      "answer": "No",
      "question_type": "counterfactual_reasoning",
      "question_rung": "counterfactual",
      "answer_type": "yes_no"
    },
    {
      "question": "Was the fact that the cyan metal sphere collided with the purple metal cylinder sufficient for the purple metal cylinder to move?",
      "answer": "Yes",
      "question_type": "sufficient_cause",
      "question_rung": "counterfactual",
      "answer_type": "yes_no"
    },
    {
      "question": "Was the fact that the purple metal cube did not collide with the cyan metal sphere sufficient for the purple metal cylinder to move?",
      "answer": "No",
      "question_type": "sufficient_cause",
      "question_rung": "counterfactual",
      "answer_type": "yes_no"
    },
    {
      "question": "Was the fact that the yellow metal cylinder collided with the purple metal cube sufficient for the purple metal cylinder to move?",
      "answer": "No",
      "question_type": "sufficient_cause",
      "question_rung": "counterfactual",
      "answer_type": "yes_no"
    },
    {
      "question": "Was the fact that the cyan metal sphere collided with the purple metal cylinder necessary for the purple metal cylinder to move?",
      "answer": "Yes",
      "question_type": "necessary_cause",
      "question_rung": "counterfactual",
      "answer_type": "yes_no"
    },
    {
      "question": "Was the fact that the purple metal cube did not collide with the cyan metal sphere necessary for the purple metal cylinder to move?",
      "answer": "Yes",
      "question_type": "necessary_cause",
      "question_rung": "counterfactual",
      "answer_type": "yes_no"
    },
    {
      "question": "Was the fact that the yellow metal cylinder collided with the purple metal cube necessary for the purple metal cylinder to move?",
      "answer": "Yes",
      "question_type": "necessary_cause",
      "question_rung": "counterfactual",
      "answer_type": "yes_no"
    },
    {
      "question": "What is the actual cause of the purple metal cylinder moving?",
      "answer": {
        "HP": [
          0,
          2,
          4,
          5,
          6
        ],
        "BV": [
          0,
          2,
          4,
          5,
          6
        ],
        "DBV": [
          2,
          4
        ],
        "Boc": [
          0,
          2,
          4,
          5,
          6
        ]
      },
      "question_type": "actual_cause",
      "question_rung": "counterfactual",
      "answer_type": "multi_choice",
      "options": [
        "The purple metal cube does not collide with the cyan metal sphere.",
        "None.",
        "The cyan metal sphere collides with the purple metal cylinder.",
        "The purple metal cube moves toward the cyan metal sphere.",
        "The cyan metal sphere moves toward the purple metal cylinder.",
        "The yellow metal cylinder moves toward the purple metal cube.",
        "The yellow metal cylinder collides with the purple metal cube."
      ]
    },
    {
      "question": "Was the fact that the cyan metal sphere collided with the purple metal cylinder responsible for the purple metal cylinder moving?",
      "answer": "Yes",
      "question_type": "responsibility",
      "question_rung": "counterfactual",
      "answer_type": "yes_no"
    },
    {
      "question": "Was the fact that the purple metal cube did not collide with the cyan metal sphere responsible for the purple metal cylinder moving?",
      "answer": "No",
      "question_type": "responsibility",
      "question_rung": "counterfactual",
      "answer_type": "yes_no"
    },
    {
      "question": "Was the fact that the yellow metal cylinder collided with the purple metal cube responsible for the purple metal cylinder moving?",
      "answer": "No",
      "question_type": "responsibility",
      "question_rung": "counterfactual",
      "answer_type": "yes_no"
    }
  ],
  "causal_graph": {
    "variables": {
      "X1": "The cyan metal sphere's collision with the purple metal cylinder",
      "X2": "The purple metal cube's collision with the cyan metal sphere",
      "X3": "The yellow metal cylinder's collision with the purple metal cube",
      "Z1": "The cyan metal sphere's motion toward the purple metal cylinder",
      "Z2": "The purple metal cube's motion toward the cyan metal sphere",
      "Z3": "The yellow metal cylinder's motion toward the purple metal cube",
      "Y": "The purple metal cylinder's motion"
    },
    "edges": [
      "Z1 -> X1",
      "Z2 -> X2",
      "Z2 -> X3",
      "Z3 -> X3",
      "X1 -> Y",
      "X2 -> X1",
      "X3 -> X2"
    ]
  },
  "twin_network": {
    "factual_world": "Z1=1, Z2=1, Z3=1, X1=1, X2=0, X3=1, Y=1",
    "counterfactual_world": {
      "do(X1=0)": "Z1=1, Z2=?, Z3=?, X2=?, X3=?, Y=0",
      "do(X2=1)": "Z1=1, Z2=1, Z3=?, X1=0, X3=?, Y=0",
      "do(X3=0)": "Z1=1, Z2=1, Z3=1, X1=0, X2=1, Y=0"
    }
  },
  "generation_metadata": {
    "scenario": "double",
    "setting": "basic",
    "total_questions": 20,
    "question_types": [
      "causality_identification",
      "responsibility",
      "causal_attribution",
      "actual_cause",
      "individual_causal_effect",
      "necessary_cause",
      "sufficient_cause",
      "counterfactual_reasoning"
    ],
    "answer_types": [
      "multi_choice",
      "yes_no"
    ]
  }
}